brigadier/__init__.py
brigadier/ambiguity_consumer.py
brigadier/command_dispatcher.py
brigadier/literal_message.py
brigadier/parse_result.py
brigadier/result_consumer.py
brigadier/string_reader.py
brigadier/arguments/__init__.py
brigadier/arguments/bool_argument_type.py
brigadier/arguments/float_argument_type.py
brigadier/arguments/integer_argument_type.py
brigadier/arguments/string_argument_type.py
brigadier/builder/__init__.py
brigadier/builder/argument_builder.py
brigadier/builder/literal_argument_builder.py
brigadier/builder/required_argument_builder.py
brigadier/context/__init__.py
brigadier/context/command_context.py
brigadier/context/command_context_builder.py
brigadier/context/parsed_argument.py
brigadier/context/parsed_command_node.py
brigadier/context/string_range.py
brigadier/context/suggestion_context.py
brigadier/exceptions/__init__.py
brigadier/exceptions/built_in_exceptions.py
brigadier/exceptions/command_expection.py
brigadier/exceptions/command_syntax_exception.py
brigadier/exceptions/dynamic_command_exception.py
brigadier/exceptions/simple_command_exception.py
brigadier/suggestion/__init__.py
brigadier/suggestion/integer_suggestion.py
brigadier/suggestion/suggestion.py
brigadier/suggestion/suggestions.py
brigadier/suggestion/suggestions_builder.py
brigadier/tree/__init__.py
brigadier/tree/argument_command_node.py
brigadier/tree/command_node.py
brigadier/tree/literal_command_node.py
brigadier/tree/root_command_node.py
brigadier.py-1.1.0.dist-info/LICENSE
brigadier.py-1.1.0.dist-info/METADATA
brigadier.py-1.1.0.dist-info/WHEEL
brigadier.py-1.1.0.dist-info/top_level.txt
brigadier.py-1.1.0.dist-info/RECORD
