Metadata-Version: 2.1
Name: brigadier.py
Version: 1.1.0
Summary: Implementation of Mojang's brigadier in Python
Home-page: https://github.com/thelennylord/brigadier.py
Author: thelennylord
License: MIT
Platform: UNKNOWN
Classifier: License :: OSI Approved :: MIT License
Classifier: Operating System :: OS Independent
Classifier: Intended Audience :: Developers
Classifier: Natural Language :: English
Classifier: Programming Language :: Python :: 3.7
Classifier: Programming Language :: Python :: 3.8
Classifier: Topic :: Software Development :: Libraries
Classifier: Topic :: Software Development :: Libraries :: Python Modules
Requires-Python: >=3.7
